toy_lof_local_outliers_factor.py
toy_lof_local_outliers_factor-0.1.0.dist-info/LICENSE
toy_lof_local_outliers_factor-0.1.0.dist-info/METADATA
toy_lof_local_outliers_factor-0.1.0.dist-info/WHEEL
toy_lof_local_outliers_factor-0.1.0.dist-info/top_level.txt
toy_lof_local_outliers_factor-0.1.0.dist-info/RECORD
