Metadata-Version: 2.1
Name: toy-lof-local-outliers-factor
Version: 0.1.0
Summary: Python implementation of Local Outlier Factor algorithm.
Author: Damjan Kužnar
License: MIT
Classifier: Programming Language :: Python :: 3
Classifier: License :: OSI Approved :: MIT License
Classifier: Operating System :: OS Independent
Requires-Python: >=3.7
License-File: LICENSE
